madewithclay/__init__.py
madewithclay/_modidx.py
madewithclay/data.py
madewithclay/embeddings.py
madewithclay/model.py
madewithclay-0.0.5.dist-info/LICENSE
madewithclay-0.0.5.dist-info/METADATA
madewithclay-0.0.5.dist-info/WHEEL
madewithclay-0.0.5.dist-info/entry_points.txt
madewithclay-0.0.5.dist-info/top_level.txt
madewithclay-0.0.5.dist-info/RECORD
