Metadata-Version: 2.1
Name: madewithclay
Version: 0.0.5
Summary: SDK to use Clay, the AI for Earth
Home-page: https://github.com/Clay-foundation/documentation
Author: Clay and collaborators
Author-email: info@madewithclay.org
License: Apache Software License 2.0
Keywords: EO AI ML Geospatial Remote-Sensing foundational-models
Classifier: Development Status :: 2 - Pre-Alpha
Classifier: Intended Audience :: Developers
Classifier: Natural Language :: English
Classifier: Programming Language :: Python :: 3.7
Classifier: Programming Language :: Python :: 3.8
Classifier: Programming Language :: Python :: 3.9
Classifier: Programming Language :: Python :: 3.10
Classifier: License :: OSI Approved :: Apache Software License
Requires-Python: >=3.7
License-File: LICENSE
Requires-Dist: geopandas
Requires-Dist: tqdm
Requires-Dist: contextily
Requires-Dist: matplotlib
Requires-Dist: pandas
Requires-Dist: numpy
Requires-Dist: pyarrow
Requires-Dist: psycopg2
Requires-Dist: geoalchemy2
Requires-Dist: setuptools
Requires-Dist: huggingface-hub
Provides-Extra: dev
